LICENSE.txt
MANIFEST.in
README.rst
setup.py
pymple/__init__.py
pymple/container.py
pymple/test_container.py
pymple.egg-info/PKG-INFO
pymple.egg-info/SOURCES.txt
pymple.egg-info/dependency_links.txt
pymple.egg-info/top_level.txt