Metadata-Version: 1.1
Name: pymple
Version: 0.1.2
Summary: A simple Inversion of Control container
Home-page: https://github.com/Raydiation/pymple
Author: Bernhard Posselt
Author-email: dev@bernhard-posselt.com
License: GPL
Keywords: pymple,ioc,inversion of control,container,dependency injection
Platform: UNKNOWN
Classifier: Intended Audience :: Developers
Classifier: License :: OSI Approved :: GNU General Public License v3 or later (GPLv3+)
Classifier: Programming Language :: Python :: 3 :: Only
Classifier: Topic :: Software Development :: Libraries
